odoo/addons/l10n_fr_hr_rup/README.rst
odoo/addons/l10n_fr_hr_rup/__init__.py
odoo/addons/l10n_fr_hr_rup/__manifest__.py
odoo/addons/l10n_fr_hr_rup/data/report_paperformat.xml
odoo/addons/l10n_fr_hr_rup/demo/demo.xml
odoo/addons/l10n_fr_hr_rup/i18n/l10n_fr_hr_rup.pot
odoo/addons/l10n_fr_hr_rup/models/__init__.py
odoo/addons/l10n_fr_hr_rup/models/hr_contract.py
odoo/addons/l10n_fr_hr_rup/models/hr_employee.py
odoo/addons/l10n_fr_hr_rup/models/hr_employee_pcs.py
odoo/addons/l10n_fr_hr_rup/readme/CONTRIBUTORS.rst
odoo/addons/l10n_fr_hr_rup/readme/DESCRIPTION.rst
odoo/addons/l10n_fr_hr_rup/readme/ROADMAP.rst
odoo/addons/l10n_fr_hr_rup/readme/USAGE.rst
odoo/addons/l10n_fr_hr_rup/report/actions.xml
odoo/addons/l10n_fr_hr_rup/report/report_rup.xml
odoo/addons/l10n_fr_hr_rup/security/ir.model.access.csv
odoo/addons/l10n_fr_hr_rup/static/description/icon.png
odoo/addons/l10n_fr_hr_rup/static/description/index.html
odoo/addons/l10n_fr_hr_rup/views/views.xml
odoo14_addon_l10n_fr_hr_rup-14.0.1.1.0.dist-info/METADATA
odoo14_addon_l10n_fr_hr_rup-14.0.1.1.0.dist-info/WHEEL
odoo14_addon_l10n_fr_hr_rup-14.0.1.1.0.dist-info/top_level.txt
odoo14_addon_l10n_fr_hr_rup-14.0.1.1.0.dist-info/RECORD
